.DS_Store
.gitignore
.travis.yml
LICENSE.txt
MANIFEST.in
README.md
conftest.py
setup.cfg
setup.py
.ipynb_checkpoints/main-checkpoint.ipynb
.ipynb_checkpoints/parser-checkpoint.ipynb
chemkin8/.DS_Store
chemkin8/__init__.py
chemkin8/chemkin.py
chemkin8/example.py
chemkin8/nasapoly.sqlite
chemkin8/nucleardb.sqlite
chemkin8/parser.py
chemkin8.egg-info/PKG-INFO
chemkin8.egg-info/SOURCES.txt
chemkin8.egg-info/dependency_links.txt
chemkin8.egg-info/not-zip-safe
chemkin8.egg-info/requires.txt
chemkin8.egg-info/top_level.txt
chemkin8/tests/.DS_Store
chemkin8/tests/.coverage
chemkin8/tests/__init__.py
chemkin8/tests/rxns.xml
chemkin8/tests/rxns_irreversible.xml
chemkin8/tests/rxns_mixed.xml
chemkin8/tests/rxns_nuclear.xml
chemkin8/tests/rxns_reversible.xml
chemkin8/tests/rxnset_long.xml
chemkin8/tests/test_chemkin.py
outputs/2017-12-08T22:57:40.506186/C-11.png
outputs/2017-12-08T22:57:40.506186/C-14.png
outputs/2017-12-08T22:57:40.506186/Cf-254.png
outputs/2017-12-08T22:57:40.506186/Fe-55.png
outputs/2017-12-08T22:57:40.506186/Np-237.png
outputs/2017-12-08T22:57:40.506186/Ra-226.png
outputs/2017-12-08T22:57:40.506186/Th*-234.png
outputs/2017-12-08T22:57:40.506186/Th-232.png
outputs/2017-12-08T22:57:40.506186/U-235.png
outputs/2017-12-08T22:57:40.506186/U-238.png
outputs/2017-12-08T22:57:40.506186/reac_output.txt
outputs/tests/C-14.png
outputs/tests/Rn-222.png