Metadata-Version: 1.0
Name: chemkin8
Version: 1.4
Summary: A Chemical Kinetics Library
Home-page: https://github.com/G8-CS207F17/cs207-FinalProject
Author: Mehul Smriti Raje, Ruiqi Chen, Ziqi Guo,
Author-email: zguo@g.harvard.edu
License: Harvard
Platform: UNKNOWN
